interfaces/__init__.py
pypescript_interface-0.0.7.dist-info/METADATA
pypescript_interface-0.0.7.dist-info/WHEEL
pypescript_interface-0.0.7.dist-info/top_level.txt
pypescript_interface-0.0.7.dist-info/RECORD
